CHANGES.rst
CONTRIBUTORS.rst
DEVELOP.rst
LICENSE.GPL
LICENSE.rst
MANIFEST.in
README.rst
setup.cfg
setup.py
docs/index.rst
src/pst/__init__.py
src/pst.restapi.egg-info/PKG-INFO
src/pst.restapi.egg-info/SOURCES.txt
src/pst.restapi.egg-info/dependency_links.txt
src/pst.restapi.egg-info/entry_points.txt
src/pst.restapi.egg-info/namespace_packages.txt
src/pst.restapi.egg-info/not-zip-safe
src/pst.restapi.egg-info/requires.txt
src/pst.restapi.egg-info/top_level.txt
src/pst/restapi/__init__.py
src/pst/restapi/configure.zcml
src/pst/restapi/interfaces.py
src/pst/restapi/permissions.zcml
src/pst/restapi/setuphandlers.py
src/pst/restapi/testing.py
src/pst/restapi/upgrades.py
src/pst/restapi/upgrades.zcml
src/pst/restapi/browser/__init__.py
src/pst/restapi/browser/configure.zcml
src/pst/restapi/browser/overrides/.gitkeep
src/pst/restapi/browser/static/.gitkeep
src/pst/restapi/locales/README.rst
src/pst/restapi/locales/__init__.py
src/pst/restapi/locales/pst.restapi.pot
src/pst/restapi/locales/update.py
src/pst/restapi/locales/update.sh
src/pst/restapi/locales/en/LC_MESSAGES/pst.restapi.mo
src/pst/restapi/locales/en/LC_MESSAGES/pst.restapi.po
src/pst/restapi/locales/fr/LC_MESSAGES/pst.restapi.mo
src/pst/restapi/locales/fr/LC_MESSAGES/pst.restapi.po
src/pst/restapi/profiles/default/browserlayer.xml
src/pst/restapi/profiles/default/catalog.xml
src/pst/restapi/profiles/default/metadata.xml
src/pst/restapi/profiles/default/registry.xml
src/pst/restapi/profiles/default/rolemap.xml
src/pst/restapi/profiles/uninstall/browserlayer.xml
src/pst/restapi/serializer/__init__.py
src/pst/restapi/serializer/action.py
src/pst/restapi/serializer/configure.zcml
src/pst/restapi/serializer/operational_objective.py
src/pst/restapi/serializer/strategic_objective.py
src/pst/restapi/tests/__init__.py
src/pst/restapi/tests/test_robot.py
src/pst/restapi/tests/test_setup.py
src/pst/restapi/tests/robot/test_example.robot